mongo_logger/__init__.py
mongo_logger/main.py
mongo_logger_2025-0.1.0.dist-info/METADATA
mongo_logger_2025-0.1.0.dist-info/WHEEL
mongo_logger_2025-0.1.0.dist-info/top_level.txt
mongo_logger_2025-0.1.0.dist-info/RECORD
